CHANGES.txt
LICENSE.txt
MANIFEST.in
README.rst
setup.py
tests/__init__.py
tests/test_textbisect.py
textbisect/__init__.py
textbisect.egg-info/PKG-INFO
textbisect.egg-info/SOURCES.txt
textbisect.egg-info/dependency_links.txt
textbisect.egg-info/top_level.txt